prng_algorithms_package/ICG_module.py
prng_algorithms_package/LCG64_32_ext_module.py
prng_algorithms_package/Ran64_module.py
prng_algorithms_package/SplitMix64_module.py
prng_algorithms_package/XSM64_module.py
prng_algorithms_package/__init__.py
pure_prng_package/__init__.py
pure_prng_package/pure_prng_module.py
pure_prng-2.9.0.dist-info/LICENSE
pure_prng-2.9.0.dist-info/METADATA
pure_prng-2.9.0.dist-info/WHEEL
pure_prng-2.9.0.dist-info/top_level.txt
pure_prng-2.9.0.dist-info/RECORD
