Metadata-Version: 2.1
Name: pure-prng
Version: 2.9.0
Summary: Generate professional pseudo-random number package in python.
Home-page: https://github.com/fsssosei/Pure_PRNG
Author: sosei
Author-email: fss.sosei@gmail.com
License: GNU Affero General Public License v3
Keywords: PRNG,Random,Multiple-precision,Variable-period
Platform: UNKNOWN
Classifier: Development Status :: 5 - Production/Stable
Classifier: License :: OSI Approved :: GNU Affero General Public License v3
Classifier: Programming Language :: Python :: 3.8
Requires-Python: >=3.8
Requires-Dist: gmpy2 (>=2.0.8)
Requires-Dist: randomgen (>=1.20.3)
Requires-Dist: pure-nrng (>=1.1.0)
